MailClientLibrary/__init__.py
MailClientLibrary/version.py
MailClientLibrary/keywords/__init__.py
MailClientLibrary/keywords/imap.py
MailClientLibrary/keywords/pop3.py
MailClientLibrary/keywords/setter.py
MailClientLibrary/keywords/smtp.py
MailClientLibrary/mailclient/__init__.py
MailClientLibrary/mailclient/errors.py
MailClientLibrary/mailclient/mail.py
MailClientLibrary/mailclient/variables.py
MailClientLibrary/mailclient/protocols/__init__.py
MailClientLibrary/mailclient/protocols/imap.py
MailClientLibrary/mailclient/protocols/pop3.py
MailClientLibrary/mailclient/protocols/smtp.py
robotframework_mailclient-0.0.14.dist-info/licenses/LICENSE
robotframework_mailclient-0.0.14.dist-info/METADATA
robotframework_mailclient-0.0.14.dist-info/WHEEL
robotframework_mailclient-0.0.14.dist-info/top_level.txt
robotframework_mailclient-0.0.14.dist-info/RECORD
