Metadata-Version: 2.4
Name: robotframework-mailclient
Version: 0.0.14
Summary: Mail Client library for Robot Framework
Home-page: https://github.com/noubar/RobotFramework-MailClientLibrary
Author: noubar
License: Apache License 2.0
Keywords: robotframework testing testautomation mailtesting mailclient mail imap smtp pop3
Platform: any
Classifier: Development Status :: 5 - Production/Stable
Classifier: Operating System :: OS Independent
Classifier: Programming Language :: Python
Classifier: Programming Language :: Python :: 3
Classifier: Programming Language :: Python :: 3.8
Classifier: Programming Language :: Python :: 3.9
Classifier: Programming Language :: Python :: 3.10
Classifier: Programming Language :: Python :: 3.11
Classifier: Programming Language :: Python :: 3.12
Classifier: Programming Language :: Python :: 3.13
Classifier: License :: OSI Approved :: MIT License
Classifier: Topic :: Software Development :: Testing
Classifier: Topic :: Communications :: Email :: Email Clients (MUA)
Classifier: Topic :: Communications :: Email :: Post-Office :: IMAP
Classifier: Topic :: Communications :: Email :: Post-Office :: POP3
Classifier: Topic :: Communications :: Email
Classifier: Framework :: Robot Framework
Classifier: Framework :: Robot Framework :: Library
Requires-Python: >=3.8, <4
License-File: LICENSE
Requires-Dist: robotframework>=4.1.3
Requires-Dist: robotframework-pythonlibcore>=4.4.1
Dynamic: author
Dynamic: classifier
Dynamic: description
Dynamic: description-content-type
Dynamic: home-page
Dynamic: keywords
Dynamic: license
Dynamic: license-file
Dynamic: platform
Dynamic: requires-dist
Dynamic: requires-python
Dynamic: summary
